pyWiseTools/__init__.py
pyWiseTools/pyWiseText.py
pyWiseTools/pyWiseVisual.py
pyWiseTools/misc_utils/__init__.py
pyWiseTools/misc_utils/update_libraries.py
pyWiseTools-0.1.2.dist-info/METADATA
pyWiseTools-0.1.2.dist-info/WHEEL
pyWiseTools-0.1.2.dist-info/top_level.txt
pyWiseTools-0.1.2.dist-info/RECORD
