Metadata-Version: 2.1
Name: pyWiseTools
Version: 0.1.2
Summary: A description of your package
Home-page: https://github.com/coralexbadea/pyWiseTools
Author: Your Name
Author-email: your.email@example.com
Classifier: Development Status :: 3 - Alpha
Classifier: License :: OSI Approved :: MIT License
Classifier: Programming Language :: Python :: 3
Classifier: Programming Language :: Python :: 3.6
Classifier: Programming Language :: Python :: 3.7
Classifier: Programming Language :: Python :: 3.8
Classifier: Programming Language :: Python :: 3.9
Classifier: Programming Language :: Python :: 3.10
Requires-Dist: numpy
Requires-Dist: pytesseract
Requires-Dist: pyautogui
Requires-Dist: opencv-python
